geo_spider.py
geo_spider-0.0.5.dist-info/METADATA
geo_spider-0.0.5.dist-info/WHEEL
geo_spider-0.0.5.dist-info/entry_points.txt
geo_spider-0.0.5.dist-info/top_level.txt
geo_spider-0.0.5.dist-info/RECORD
