Metadata-Version: 2.1
Name: geo-spider
Version: 0.0.5
Summary: Crawling all GEO metadata.
Home-page: https://github.com/soultoolman/geo-spider
Author: soultoolman
Author-email: soultooman@gmail.com
License: MIT
Platform: UNKNOWN
Classifier: License :: OSI Approved :: MIT License
Classifier: Programming Language :: Python
Classifier: Programming Language :: Python :: 3
Classifier: Programming Language :: Python :: 3.6
Classifier: Programming Language :: Python :: Implementation :: CPython
Classifier: Programming Language :: Python :: Implementation :: PyPy
Classifier: Topic :: Scientific/Engineering :: Bio-Informatics
Requires-Python: >=3.6.0
Requires-Dist: click
Requires-Dist: scrapy
Requires-Dist: jsonlines
Requires-Dist: geo-alchemy
